LICENSE.txt
README.md
setup.py
deepmed/DeepMed_bin.py
deepmed/DeepMed_bin_cv.py
deepmed/DeepMed_cont.py
deepmed/DeepMed_cont_cv.py
deepmed/DeepMed_cv.py
deepmed/__init__.py
deepmed/dnn.py
deepmed/gbm.py
deepmed/lasso.py
deepmed/main.py
deepmed/ml_cv.py
deepmed/rf.py
deepmed.egg-info/PKG-INFO
deepmed.egg-info/SOURCES.txt
deepmed.egg-info/dependency_links.txt
deepmed.egg-info/requires.txt
deepmed.egg-info/top_level.txt