Metadata-Version: 2.1
Name: deepmed
Version: 0.2.2
Summary: An approach for semi-parametric causal mediation analysis to estimate the natural (in)direct effects of a binary treatment on an outcome of interest.
Home-page: https://github.com/Gloriagao0624/DeepMed_Python
Author: Ge Gao
Author-email: <gg2797@columbia.edu>
License: MIT
Keywords: Causal mediation analysis,Semiparametric causal inference,Deep neural networks
Classifier: Intended Audience :: Science/Research
Classifier: License :: OSI Approved :: MIT License
Classifier: Programming Language :: Python :: 3
License-File: LICENSE.txt
